everywhere/__init__.py
everywhere/impl.py
everywhere-1.1.dist-info/LICENSE
everywhere-1.1.dist-info/METADATA
everywhere-1.1.dist-info/WHEEL
everywhere-1.1.dist-info/top_level.txt
everywhere-1.1.dist-info/RECORD
