Metadata-Version: 2.1
Name: everywhere
Version: 1.1
Summary: A globaly importable thread local variable. This utility package is literally two lines of code.
Home-page: https://github.com/SimonRovder/everywhere
Author: Simon Rovder
Author-email: simon.rovder@gmail.com
License: GPL
Platform: UNKNOWN
Classifier: Programming Language :: Python :: 3
Classifier: Operating System :: OS Independent
Requires-Python: >=3.5
